tartine.py
tartine-0.6.3.dist-info/LICENSE
tartine-0.6.3.dist-info/WHEEL
tartine-0.6.3.dist-info/METADATA
tartine-0.6.3.dist-info/RECORD
