Metadata-Version: 2.1
Name: tartine
Version: 0.6.3
Summary: Manipulate dynamic spreadsheets with arbitrary layouts using Python 
License: MIT
Author: MaxHalford
Author-email: maxhalford25@gmail.com
Requires-Python: >=3.8,<4.0
Classifier: License :: OSI Approved :: MIT License
Classifier: Programming Language :: Python :: 3
Classifier: Programming Language :: Python :: 3.10
Classifier: Programming Language :: Python :: 3.8
Classifier: Programming Language :: Python :: 3.9
Requires-Dist: glom (>=22.1.0,<23.0.0)
